sdhypermodern_python/.readthedocs.yml
sdhypermodern_python/__init__.py
sdhypermodern_python/console.py
sdhypermodern_python/requirements.txt
sdhypermodern_python/test-pypi.yml
sdhypermodern_python/wikipedia.py
sdhypermodern_python-0.3.0.dist-info/METADATA
sdhypermodern_python-0.3.0.dist-info/WHEEL
sdhypermodern_python-0.3.0.dist-info/entry_points.txt
sdhypermodern_python-0.3.0.dist-info/RECORD
